{
  "children": [
    {
      "id": "chapter-6-1",
      "type": "chapter",
      "label": "第六部論病例計酬",
      "level": 2,
      "parent_id": "part-6",
      "has_children": false,
      "metadata": {
        "filename": "6-1第六部論病例計酬-114.09.01.doc",
        "doc_id": "6-1"
      },
      "content": "第六部　　論病例計酬\n\n通則：\n一、當主診斷及主手術(或處置)碼為本部各章節所列疾病診斷碼及手術(或處置)碼時，依本部各章節所訂支付點數或相關規定申報費用。\n二、本部各章節所訂診療項目分為基本診療項目、選擇性診療項目二部份，基本診療項目之實施需達所訂基本診療項目之65％(以四捨五入取至整數位)，選擇性診療項目(或其他診療項目)若為診療必須仍應施行，惟其費用已包含於定額中不得另行申報費用。\n三、個案出院時應符合本部各章所訂出院狀態。\n四、申報費用時須詳填國際疾病臨床修訂號碼，包括診斷碼及手術(或處    置)碼，若有其他合併症時應詳填次診斷、次手術(或處置)碼。\n五、本部各章節所訂點數中，已包含病房費、診察費、藥事服務費、藥品費、各項檢查及治療處置費、注射費、麻醉費、手術費、一般材料費及特殊材料費等健保支付標準所訂相關費用。\n六、本部各章節所訂項目，若未依規定完成治療，保險對象即因故出院    者，整筆醫療費用應按實際醫療費用申報。\n七、本部各章節所述「實際醫療費用」應以本部以外其他各章節所訂點數    計算。\n八、本部各章節中基本診療項目列有執行次數，每項目執行一次即視為完成，惟醫令項目之執行未依規定達65%時，以「所訂全部項目中未執行項目×其個別執行次數」為核減項次。\n九、本部各章節中基本診療項目中有※者為必要執行項目，若未執行，整    筆醫療費用不予給付。\n十、各章節中若術前、術中或術後列有相同項目時，視為一項，其執行次    數為二者之合計。\n十一、本部各章節列有「得核實申報上限點數」及「得核實申報個案數比率」，其中「得核實申報上限點數」係指各醫療院所該項手術案件中，其有次診斷或次手術(或處置)而致實際醫療費用在所列之點數以上者，得按實際醫療費用申報；「得核實申報個案數比率」係指依前述規定核實申報之個案數不得超過各醫療院所當月份該項手術個案數之比率。\n十二、本部各章節所訂項目，若有公認新療法或公認新手術方式，醫療院所應檢具相關成本資料向保險人提出申請，由保險人評估後先行訂定申報項目，供特約醫療院所適用，俟彙集項目及完整資料後，再另依全民健康保險法第四十一條辦理。\n十三、若特約醫療院所計算得核實申報個案數未達一個案例時，得有一個案例核實申報，惟應同時符合申報上限點數之規定。\n十四、特約醫療院所門診論病例計酬案件釋出處方者，應扣除釋出處方之藥費及藥事服務費後申報。\n十五、本部各章節所訂項目執行率為百分之百之診療項目(例如第二部第一章病房費、診察費、藥事服務費等，以及本部之必要診療項目)之支付點數有異動時，依上述診療項目計算前後點數差額，配合調整本部定額支付點數及核實申報上限點數，其中第二部第一章項目次數，依本標準所列各論病例計酬平均住院日數計算；必要診療項目次數，則依本部各診療項目要求表所列次數計算。\n十六、已導入全民健康保險住院診斷關聯群(Taiwan Diagnosis Related Groups，Tw-DRGs)之論病例計酬項目，適用Tw-DRGs之醫院應以Tw-DRGs支付標準申報。\n十七、論病例計酬案件使用符合「全民健保尚未納入給付特材管理作業要點」之「全民健保尚未納入給付特材品項表」(以下稱品項表)所列特材，排除自付差額之特材品項，其保險醫事服務機構收費、申報及健保支付方式如下：\n（一）\t病人同意使用符合品項表之特材，保險醫事服務機構應依醫療法第二十一條規定辦理。\n（二）如收取自費，保險醫事服務機構於申報論病例計酬時，應扣除被品項表特材替代之健保給付特材之支付點數，且應併同醫療費用申報。對照檔請參閱保險人全球資訊網公布之「全民健保尚未納入給付特殊材料品項(自費醫材)與替代健保給付特材品項對照檔」。\n【醫令類別應填報：「D」(被替代之特材項目)、「E」(自費特材項目-未給付)或「F」(自費特材項目-不符給付規定)。】\n（三）\t併同醫療費用申報資料：品項表（含不給付項目及不符適應症之個案）之品項代碼、單價、數量、收取自費總金額；被替代之健保給付特材品項代碼、單價、數量及支付點數。\n（四）\t品項表特材收取之自費金額，不得計入本部所稱「實際醫療費用」計算。\n十八、除病人同意使用符合「全民健保尚未納入給付特材管理作業要點」規定之品項表特材或自付差額特材品項外，不得另行向保險對象收取給付範圍費用，違反本項規定者，整筆醫療費用不予支付。\n第一章　產科\n通則：\n一、本章各項目「得核實申報上限點數」、「得核實申報個案數比率」如下表：\n\n\n二、陰道生產標準住院日數自住院日起算三天，剖腹生產標準住院日數自住院日起算六天，生產過程中有施行引產之事實者，得多住一天，惟皆依定額給付，不得另行申報費用。\n三、本章定額支付中已包括正常新生兒照護費。\n四、新生兒體重二千公克以下或因病須轉至有小兒科專科醫師之醫院診治，若未符前述情況，僅於婦產科診所保溫箱照護者，申報費用時除生產定額外不得另行申報費用或另行收費。\n五、陰道生產因有次診斷或次手術(或處置)而致實際醫療費用超過定額時(雙胞胎者以定額再加計一人次之新生兒費用為界限，多胞胎類推)，得按實際醫療費用申報。\n六、前胎剖腹產之陰道生產，實際醫療費用超過定額時（雙胞胎者以定額再加計一人次之新生兒費用為界限，多胞胎類推），得按實際醫療費用申報。\n七、陰道生產案件中，屬下列主診斷碼(ICD-10-CM)且不論有無次診斷或次手術（處置）者，得適用本章通則五之規定：\nO10-O11、O13-O16、O21-O22、O24、O34.3、O42、O43.2、O44-O46、O60.1、O60.2、O67、O72-O75、O85-O86、O87.1、O87.3、O88、O89.09、O89.8、O89.9、O90-O91、O98-O99。\n八、剖腹產案件中，其有次診斷或次手術（或處置）而致實際醫療費用超過「得核實申報上限點數」者，得按實際醫療費用申報，惟其個案數不得超過「得核實申報個案數比率」；除以上情形外之其它剖腹產個案皆依本部所訂支付點數申報費用。\n九、剖腹產案件中，屬下列主診斷碼(ICD-10-CM)且不論有無次診斷或次手術（處置）者，得適用本章通則通則八之規定：\nO10-O11、O13-O16、O21、O24、O34、O42、O44-O46、O60.1、O60.2、O99.81。\n十、本章節所述「實際醫療費用」係包括母親及新生兒費用。\n十一、陰道生產及剖腹產論病例計酬定額支付點數中已含一人次新生兒費，如為雙胞胎，得另加計一人次新生兒費（多胞胎類推）。\n十二、不符醫學上適應症而自行要求施行剖腹產者，依自行要求剖腹產(97014C)點數支付。\n\n\n附表6.1.1 陰道生產診療項目要求表\n\n\n附表6.1.2 剖腹生產診療項目要求表\n\n\n第二章　婦科\n通則：本章各項目「得核實申報上限點數」、「得核實申報個案數比率」如下表：\n\n\n\n附表6.2.1 子宮肌瘤切除術(住院)、子宮鏡子宮肌瘤切除術(住院)診療項目要求表\n\n\n附表6.2.2 輸卵管外孕手術(住院)診療項目要求表\n\n\n\n附表6.2.3 子宮完全切除術(住院)診療項目要求表\n\n附表6.2.4 次全子宮切除術(住院)診療項目要求表\n\n\n附表6.2.5 卵巢部分（全部）切除術或輸卵管卵巢切除術(住院)診療項目要求表\n\n附表6.2.6 腹腔鏡子宮完全切除術(住院)診療項目要求表\n\n\n附表6.2.7 腹腔鏡卵巢部分（全部）切除術或輸卵管卵巢切除術(住院)診療項目要求表\n\n\n\n附表6.2.8 腹腔鏡子宮外孕手術(住院)診療項目要求表\n\n\n第三章　一般外科\n通則：\n一、本章各項目「得核實申報上限點數」、「得核實申報個案數比率」如下表：\n    \n\n\n\n附表6.3.5 股及腹股溝疝氣手術（單側，門診）診療項目要求表\n\n\n第四章　泌尿科\n通則：\n一、本章各項目「得核實申報上限點數」、「得核實申報個案數比率」如下表：\n\t\n二、施行第一次尿路結石體外震波碎石術起三十日內施行第二次者，按97409K-97412A及97422B-97423B申報。\n三、尿路結石體外震波碎石術三十日內同側第三次以上治療，應檢具Ｘ光片專案申請，經保險人同意後施行，費用比照第二次申報；申報費用時應檢附保險人同意函影本以憑核付。\n四、尿路結石體外震波碎石術個案申報費用應檢附尿路結石體外震波碎石術之紀錄影本。\n\n\n附表6.4.2 尿路結石體外震波碎石術診療項目要求表\n\n\n \n第六章 眼科\n通則：\n一、本章各項目「得核實申報上限點數」、「得核實申報個案數比率」如下表：\n\n\n二、雙側水晶體囊內(外)摘除術及人工水晶體置入術非屬論病例計酬項目。\n\n\n附表6.6.2水晶體囊內(外)摘除術及人工水晶體置入術(單側) (門診)診療項目要求表\n\n\n第七章 耳鼻喉科 \n\n通則：本章各項目「得核實申報上限點數」、「得核實申報個案數比率」如下表：\n\n\n\n\n附表6.7.0 耳鼻喉科項目之國際疾病臨床分類修正代碼\n\n\n附表6.7.4 喉直達鏡並作聲帶或會厭軟骨腫瘤切除或剝去，無主要合併症或併發症(門診)診療項目要求表\n",
      "tables": [
        "doc-table-6-1第六部論病例計酬-114.09.01-s0-t0",
        "doc-table-6-1第六部論病例計酬-114.09.01-s0-t1",
        "doc-table-6-1第六部論病例計酬-114.09.01-s0-t2",
        "doc-table-6-1第六部論病例計酬-114.09.01-s0-t3",
        "doc-table-6-1第六部論病例計酬-114.09.01-s0-t4",
        "doc-table-6-1第六部論病例計酬-114.09.01-s0-t5",
        "doc-table-6-1第六部論病例計酬-114.09.01-s0-t6",
        "doc-table-6-1第六部論病例計酬-114.09.01-s0-t7",
        "doc-table-6-1第六部論病例計酬-114.09.01-s0-t8",
        "doc-table-6-1第六部論病例計酬-114.09.01-s0-t9",
        "doc-table-6-1第六部論病例計酬-114.09.01-s0-t10",
        "doc-table-6-1第六部論病例計酬-114.09.01-s0-t11",
        "doc-table-6-1第六部論病例計酬-114.09.01-s0-t12",
        "doc-table-6-1第六部論病例計酬-114.09.01-s0-t13",
        "doc-table-6-1第六部論病例計酬-114.09.01-s0-t14",
        "doc-table-6-1第六部論病例計酬-114.09.01-s0-t15",
        "doc-table-6-1第六部論病例計酬-114.09.01-s0-t16",
        "doc-table-6-1第六部論病例計酬-114.09.01-s0-t17",
        "doc-table-6-1第六部論病例計酬-114.09.01-s0-t18",
        "doc-table-6-1第六部論病例計酬-114.09.01-s0-t19",
        "doc-table-6-1第六部論病例計酬-114.09.01-s0-t20",
        "doc-table-6-1第六部論病例計酬-114.09.01-s0-t21",
        "doc-table-6-1第六部論病例計酬-114.09.01-s0-t22",
        "doc-table-6-1第六部論病例計酬-114.09.01-s0-t23",
        "doc-table-6-1第六部論病例計酬-114.09.01-s0-t24",
        "doc-table-6-1第六部論病例計酬-114.09.01-s0-t25",
        "doc-table-6-1第六部論病例計酬-114.09.01-s0-t26"
      ],
      "table_count": 27
    },
    {
      "id": "chapter-6-2",
      "type": "chapter",
      "label": "第六部附錄102.01.01(1)",
      "level": 2,
      "parent_id": "part-6",
      "has_children": false,
      "metadata": {
        "filename": "6-2第六部附錄102.01.01(1).doc",
        "doc_id": "6-2"
      },
      "content": "附錄6.1主要合併症及併發症診斷碼\n說明：\n1.病患之任一次要診斷符合表列（次診斷欄），且其主要診斷非為其主診斷欄所列者，再排除附錄二表列診斷，即為有效之「主要合併症、併發症」。\n2.前項所稱次要診斷之定義為：住院時早已與主要診斷同時存在，或是後來才發展的情況，影響到所接受的醫療及（或）住院天數者，至與此次住院無關之疾病則不包括在內。\n\n附錄6.2主要合併症、併發症除外診斷碼\n說明：病患之次診斷雖已符合附錄6.1表列，但如符合本附錄表列診斷者，則主要合併症、併發症將變為一般合併症、併發症。\n\n\n附錄6.3 一般合併症、併發症診斷碼\n說明：\n病患之任一次要診斷符合表列（次診斷欄），且其主要診斷非為其主診斷欄所列者，即為有效之「一般合併症、併發症」。\n2.前項所稱次要診斷之定義為：住院時早已與主要診斷同時存在，或是後來才發展的情況，影響到所接受的醫療及（或）住院天數者，至與此次住院無關之疾病則不包括在內。\n\n\n附錄6.4處置或手術排除診斷碼\n說明：第六部各章節中附表之「處置或手術排除碼」乙欄中列有主或任一次處置碼需排除者，其範圍為本附表所列。\n\n\n\n\n\n\n\n",
      "tables": [
        "doc-table-6-2第六部附錄102.01.01(1)-s0-t0",
        "doc-table-6-2第六部附錄102.01.01(1)-s0-t1",
        "doc-table-6-2第六部附錄102.01.01(1)-s0-t2",
        "doc-table-6-2第六部附錄102.01.01(1)-s0-t3",
        "doc-table-6-2第六部附錄102.01.01(1)-s0-t4",
        "doc-table-6-2第六部附錄102.01.01(1)-s0-t5",
        "doc-table-6-2第六部附錄102.01.01(1)-s0-t6",
        "doc-table-6-2第六部附錄102.01.01(1)-s0-t7",
        "doc-table-6-2第六部附錄102.01.01(1)-s0-t8",
        "doc-table-6-2第六部附錄102.01.01(1)-s0-t9"
      ],
      "table_count": 10
    },
    {
      "id": "chapter-6-3",
      "type": "chapter",
      "label": "第六部附表(6.7.5,6.7.5.1~6.7.5.2)",
      "level": 2,
      "parent_id": "part-6",
      "has_children": false,
      "metadata": {
        "filename": "6-3第六部附表(6.7.5,6.7.5.1~6.7.5.2)-114.01.01.xlsx",
        "doc_id": "6-3"
      }
    }
  ]
}